{
  "title": "Demo01",
  "packageName": "",
  "startScene": "da39fe19-1fde-482d-8b61-d7e2de2411d6",
  "excludeScenes": [],
  "includeSDKBox": false,
  "orientation": {
    "landscapeLeft": true,
    "landscapeRight": true,
    "portrait": false,
    "upsideDown": false
  },
  "webOrientation": "auto",
  "inlineSpriteFrames": true,
  "inlineSpriteFrames_native": true,
  "mergeStartScene": false,
  "optimizeHotUpdate": true,
  "md5Cache": false,
  "encryptJs": false,
  "xxteaKey": "1979494a-7ea4-42",
  "zipCompressJs": true,
  "fb-instant-games": {},
  "android": {
    "packageName": ""
  },
  "ios": {
    "packageName": ""
  },
  "mac": {
    "packageName": ""
  },
  "win32": {},
  "android-instant": {
    "REMOTE_SERVER_ROOT": "",
    "host": "",
    "packageName": "",
    "pathPattern": "",
    "recordPath": "",
    "scheme": "https",
    "skipRecord": false
  },
  "appBundle": false,
  "includeAnySDK": false
}
